safetydance_django/__init__.py
safetydance_django/steps.py
safetydance_django/test.py
safetydance_django-0.0.6.dist-info/LICENSE.txt
safetydance_django-0.0.6.dist-info/WHEEL
safetydance_django-0.0.6.dist-info/METADATA
safetydance_django-0.0.6.dist-info/RECORD
